README.md
setup.cfg
setup.py
checksum_v2/PaytmChecksum.py
checksum_v2/__init__.py
checksum_v2/sample.py
testing_python_again.egg-info/PKG-INFO
testing_python_again.egg-info/SOURCES.txt
testing_python_again.egg-info/dependency_links.txt
testing_python_again.egg-info/top_level.txt