Metadata-Version: 1.1
Name: testing-python-again
Version: 1.3.0
Summary: Testpay Python Client
Home-page: https://github.com/soumya-vats/testpython
Author: Team Testpay
Author-email: UNKNOWN
License: MIT
Keywords: Testpay payment gateway india
Platform: UNKNOWN
Classifier: Development Status :: 4 - Beta
Classifier: Intended Audience :: Developers
Classifier: License :: OSI Approved :: MIT License
Classifier: Programming Language :: Python
Classifier: Programming Language :: Python :: 2
Classifier: Programming Language :: Python :: 2.7
Classifier: Programming Language :: Python :: 3
Classifier: Programming Language :: Python :: 3.3
Classifier: Programming Language :: Python :: 3.4
Classifier: Programming Language :: Python :: 3.5
Classifier: Programming Language :: Python :: 3.6
Classifier: Topic :: Software Development :: Libraries :: Python Modules
